stocks_api/__init__.py
stocks_api/config.py
stocks_api/delay.py
stocks_api/stocks.py
Stocks_API-0.0.5.dist-info/METADATA
Stocks_API-0.0.5.dist-info/WHEEL
Stocks_API-0.0.5.dist-info/top_level.txt
Stocks_API-0.0.5.dist-info/RECORD
