Metadata-Version: 2.1
Name: Stocks-API
Version: 0.0.5
Summary: A small package for pulling stockmarket data via the free Polygon.io API
Author: Rene Alby
Author-email: Rene Alby <rene.alby@gmail.com>
Project-URL: Homepage, https://github.com/Reneige/stocks_api
Classifier: Programming Language :: Python :: 3
Classifier: License :: OSI Approved :: MIT License
Classifier: Operating System :: OS Independent
Requires-Python: >=3.7
Requires-Dist: pandas
Requires-Dist: lxml
Requires-Dist: requests
